Workbook
Name AccountTypes: _Lists!$A$2:$A$6
Name AccountUsages: _Lists!$B$2:$B$3
Name YesNo: _Lists!$C$2:$C$3
Name Currencies: _Lists!$D$2:$D$6
Name TagExamples: _Lists!$E$2:$E$16

Sheet Read Me
A1: Mopane CBS — Accounting data request
A2: Please complete sheets 1 and 2, then return this file. Do not rename the sheets or the header row.
A4: What we need
A5: We need two datasets from your current accounting system so we can set up the chart of accounts and opening GL balances in Mopane CBS. 1. Chart of Accounts — every GL account (headers and postable accounts). 2. Opening Trial Balance — the debit or credit balance of each postable account as at the cutover date, per office and currency. Fill the yellow cells. Leave unused rows blank. Use the Example sheet if you are unsure.
A8: How to complete the file
A9: • Use Excel or LibreOffice. Keep this file as .xlsx. • Put GL codes as text (so 0010 is not converted to 10). The GL Code columns are already formatted as text. • GL Code must be unique and identical on both sheets — this is how we match balances to accounts. • HEADER accounts are grouping/parent accounts only. DETAIL accounts are the ones you post to. • Opening balances go on DETAIL accounts only. Do not put balances on HEADER accounts. • Each trial-balance row should have either a Debit or a Credit, not both. • The trial balance must balance: total Debits = total Credits. Check the status box on sheet 2. • One cutover date, one currency and one office per file is preferred. If you have several offices or currencies, either add extra rows (override Office / Currency) or send a copy of this file per office/currency. • Do not include loan-by-loan or savings-by-account listings here. This file is GL only.
A12: Account types (sheet 1)
A13: Account Type | B13: Normal balance | C13: Typical examples
A14: ASSET | B14: Debit | C14: Cash, bank, loan portfolio, receivables, fixed assets
A15: LIABILITY | B15: Credit | C15: Client savings, payables, borrowings
A16: EQUITY | B16: Credit | C16: Share capital, retained earnings, opening-balance contra
A17: INCOME | B17: Credit | C17: Interest income, fees, other income
A18: EXPENSE | B18: Debit | C18: Interest expense, salaries, operating costs
A20: Important constraints
A21: Opening balances can only be loaded before any other journals have been posted in CBS. Please give us a balanced trial balance as at the agreed cutover date, not a P&L for a period. Income and expense accounts may have opening balances if you are mid-year; otherwise they are usually zero and YTD activity starts after go-live. Please also confirm: legal entity / office name(s), reporting currency, and the cutover date. If your current system uses a different account numbering scheme, keep your existing GL codes — we will import them as-is.
A23: Questions?
A24: If a column is unclear, look at the Example sheet or the comments on the column headers (hover the small red triangle). Return the completed file as .xlsx — no PDF, no screenshot.

Sheet 1. Chart of Accounts
A1: 1. Chart of Accounts
A2: One row per GL account. Yellow cells are for you to complete. HEADER = grouping only; DETAIL = postable.
A3: Tip: enter parents before children. Parent GL Code should be a HEADER account. Leave Parent GL Code blank for top-level headers. Tag can be a simple label (Cash, Bank, Default) — we will map it in CBS.
A5: Account Type* | B5: Account Name* | C5: Account Usage* | D5: Manual entries allowed* | E5: Parent GL Code | F5: GL Code* | G5: Tag* | H5: Description* | I5: Status (auto) | J5: Notes
I6: =IF(F6="","",IF(COUNTIF($F$6:$F$505,F6)>1,"DUPLICATE GL CODE",IF(OR(A6="",B6="",C6="",D6="",G6="",H6=""),"INCOMPLETE","OK")))
I7: =IF(F7="","",IF(COUNTIF($F$6:$F$505,F7)>1,"DUPLICATE GL CODE",IF(OR(A7="",B7="",C7="",D7="",G7="",H7=""),"INCOMPLETE","OK")))
I8: =IF(F8="","",IF(COUNTIF($F$6:$F$505,F8)>1,"DUPLICATE GL CODE",IF(OR(A8="",B8="",C8="",D8="",G8="",H8=""),"INCOMPLETE","OK")))
I9: =IF(F9="","",IF(COUNTIF($F$6:$F$505,F9)>1,"DUPLICATE GL CODE",IF(OR(A9="",B9="",C9="",D9="",G9="",H9=""),"INCOMPLETE","OK")))
I10: =IF(F10="","",IF(COUNTIF($F$6:$F$505,F10)>1,"DUPLICATE GL CODE",IF(OR(A10="",B10="",C10="",D10="",G10="",H10=""),"INCOMPLETE","OK")))
I11: =IF(F11="","",IF(COUNTIF($F$6:$F$505,F11)>1,"DUPLICATE GL CODE",IF(OR(A11="",B11="",C11="",D11="",G11="",H11=""),"INCOMPLETE","OK")))
I12: =IF(F12="","",IF(COUNTIF($F$6:$F$505,F12)>1,"DUPLICATE GL CODE",IF(OR(A12="",B12="",C12="",D12="",G12="",H12=""),"INCOMPLETE","OK")))
I13: =IF(F13="","",IF(COUNTIF($F$6:$F$505,F13)>1,"DUPLICATE GL CODE",IF(OR(A13="",B13="",C13="",D13="",G13="",H13=""),"INCOMPLETE","OK")))
I14: =IF(F14="","",IF(COUNTIF($F$6:$F$505,F14)>1,"DUPLICATE GL CODE",IF(OR(A14="",B14="",C14="",D14="",G14="",H14=""),"INCOMPLETE","OK")))
I15: =IF(F15="","",IF(COUNTIF($F$6:$F$505,F15)>1,"DUPLICATE GL CODE",IF(OR(A15="",B15="",C15="",D15="",G15="",H15=""),"INCOMPLETE","OK")))
I16: =IF(F16="","",IF(COUNTIF($F$6:$F$505,F16)>1,"DUPLICATE GL CODE",IF(OR(A16="",B16="",C16="",D16="",G16="",H16=""),"INCOMPLETE","OK")))
I17: =IF(F17="","",IF(COUNTIF($F$6:$F$505,F17)>1,"DUPLICATE GL CODE",IF(OR(A17="",B17="",C17="",D17="",G17="",H17=""),"INCOMPLETE","OK")))
... I505: =IF(F505="","",IF(COUNTIF($F$6:$F$505,F505)>1,"DUPLICATE GL CODE",IF(OR(A505="",B505="",C505="",D505="",G505="",H505=""),"INCOMPLETE","OK")))

Sheet 2. Opening Balances
A1: 2. Opening Trial Balance
A2: Balances of DETAIL accounts as at cutover. Total Debits must equal Total Credits. Do not include HEADER accounts.
A3: Complete once — copied onto each row when you enter a GL Code | G3: Balance check (must be zero)
A4: Office name* | C4: Exact office name as it will appear in CBS, e.g. Head Office | G4: Total Debits | H4: =SUM(F11:F510)
A5: Cutover / as-at date* | C5: Last day of the old system, e.g. 31/12/2025 | G5: Total Credits | H5: =SUM(G11:G510)
A6: Currency (ISO)* | C6: e.g. USD or ZWG — must be a currency enabled in CBS | G6: Difference (Dr − Cr) | H6: =H4-H5
A7: Enter DETAIL accounts only. Leave Debit or Credit blank (do not put 0 on both). Office, Date and Currency on each row are filled from the yellow box when you type a GL Code — override a row if you have more than one office or currency. | G7: =IF(AND(H4=0,H5=0),"Enter balances below",IF(ABS(H6)<0.005,"BALANCED — ready to send","NOT BALANCED — total Debits must equal total Credits"))
A10: Office Name* | B10: As-at Date* | C10: Currency* | D10: GL Code* | E10: Account Name | F10: Debit | G10: Credit | H10: Line check (auto) | I10: Notes | J10: Matches COA? (auto)
A11: =IF(D11="","",$B$4) | B11: =IF(D11="","",$B$5) | C11: =IF(D11="","",$B$6) | H11: =IF(D11="","",IF(AND(N(F11)>0,N(G11)>0),"ERROR — debit AND credit",IF(AND(N(F11)=0,N(G11)=0),"ERROR — no amount","OK"))) | J11: =IF(D11="","",IF(COUNTIF('1. Chart of Accounts'!$F$6:$F$505,D11)=0,"NOT ON CHART OF ACCOUNTS","Found on COA"))
A12: =IF(D12="","",$B$4) | B12: =IF(D12="","",$B$5) | C12: =IF(D12="","",$B$6) | H12: =IF(D12="","",IF(AND(N(F12)>0,N(G12)>0),"ERROR — debit AND credit",IF(AND(N(F12)=0,N(G12)=0),"ERROR — no amount","OK"))) | J12: =IF(D12="","",IF(COUNTIF('1. Chart of Accounts'!$F$6:$F$505,D12)=0,"NOT ON CHART OF ACCOUNTS","Found on COA"))
A13: =IF(D13="","",$B$4) | B13: =IF(D13="","",$B$5) | C13: =IF(D13="","",$B$6) | H13: =IF(D13="","",IF(AND(N(F13)>0,N(G13)>0),"ERROR — debit AND credit",IF(AND(N(F13)=0,N(G13)=0),"ERROR — no amount","OK"))) | J13: =IF(D13="","",IF(COUNTIF('1. Chart of Accounts'!$F$6:$F$505,D13)=0,"NOT ON CHART OF ACCOUNTS","Found on COA"))
A14: =IF(D14="","",$B$4) | B14: =IF(D14="","",$B$5) | C14: =IF(D14="","",$B$6) | H14: =IF(D14="","",IF(AND(N(F14)>0,N(G14)>0),"ERROR — debit AND credit",IF(AND(N(F14)=0,N(G14)=0),"ERROR — no amount","OK"))) | J14: =IF(D14="","",IF(COUNTIF('1. Chart of Accounts'!$F$6:$F$505,D14)=0,"NOT ON CHART OF ACCOUNTS","Found on COA"))
A15: =IF(D15="","",$B$4) | B15: =IF(D15="","",$B$5) | C15: =IF(D15="","",$B$6) | H15: =IF(D15="","",IF(AND(N(F15)>0,N(G15)>0),"ERROR — debit AND credit",IF(AND(N(F15)=0,N(G15)=0),"ERROR — no amount","OK"))) | J15: =IF(D15="","",IF(COUNTIF('1. Chart of Accounts'!$F$6:$F$505,D15)=0,"NOT ON CHART OF ACCOUNTS","Found on COA"))
A16: =IF(D16="","",$B$4) | B16: =IF(D16="","",$B$5) | C16: =IF(D16="","",$B$6) | H16: =IF(D16="","",IF(AND(N(F16)>0,N(G16)>0),"ERROR — debit AND credit",IF(AND(N(F16)=0,N(G16)=0),"ERROR — no amount","OK"))) | J16: =IF(D16="","",IF(COUNTIF('1. Chart of Accounts'!$F$6:$F$505,D16)=0,"NOT ON CHART OF ACCOUNTS","Found on COA"))
A17: =IF(D17="","",$B$4) | B17: =IF(D17="","",$B$5) | C17: =IF(D17="","",$B$6) | H17: =IF(D17="","",IF(AND(N(F17)>0,N(G17)>0),"ERROR — debit AND credit",IF(AND(N(F17)=0,N(G17)=0),"ERROR — no amount","OK"))) | J17: =IF(D17="","",IF(COUNTIF('1. Chart of Accounts'!$F$6:$F$505,D17)=0,"NOT ON CHART OF ACCOUNTS","Found on COA"))
A18: =IF(D18="","",$B$4) | B18: =IF(D18="","",$B$5) | C18: =IF(D18="","",$B$6) | H18: =IF(D18="","",IF(AND(N(F18)>0,N(G18)>0),"ERROR — debit AND credit",IF(AND(N(F18)=0,N(G18)=0),"ERROR — no amount","OK"))) | J18: =IF(D18="","",IF(COUNTIF('1. Chart of Accounts'!$F$6:$F$505,D18)=0,"NOT ON CHART OF ACCOUNTS","Found on COA"))
A19: =IF(D19="","",$B$4) | B19: =IF(D19="","",$B$5) | C19: =IF(D19="","",$B$6) | H19: =IF(D19="","",IF(AND(N(F19)>0,N(G19)>0),"ERROR — debit AND credit",IF(AND(N(F19)=0,N(G19)=0),"ERROR — no amount","OK"))) | J19: =IF(D19="","",IF(COUNTIF('1. Chart of Accounts'!$F$6:$F$505,D19)=0,"NOT ON CHART OF ACCOUNTS","Found on COA"))
A20: =IF(D20="","",$B$4) | B20: =IF(D20="","",$B$5) | C20: =IF(D20="","",$B$6) | H20: =IF(D20="","",IF(AND(N(F20)>0,N(G20)>0),"ERROR — debit AND credit",IF(AND(N(F20)=0,N(G20)=0),"ERROR — no amount","OK"))) | J20: =IF(D20="","",IF(COUNTIF('1. Chart of Accounts'!$F$6:$F$505,D20)=0,"NOT ON CHART OF ACCOUNTS","Found on COA"))
A21: =IF(D21="","",$B$4) | B21: =IF(D21="","",$B$5) | C21: =IF(D21="","",$B$6) | H21: =IF(D21="","",IF(AND(N(F21)>0,N(G21)>0),"ERROR — debit AND credit",IF(AND(N(F21)=0,N(G21)=0),"ERROR — no amount","OK"))) | J21: =IF(D21="","",IF(COUNTIF('1. Chart of Accounts'!$F$6:$F$505,D21)=0,"NOT ON CHART OF ACCOUNTS","Found on COA"))
A22: =IF(D22="","",$B$4) | B22: =IF(D22="","",$B$5) | C22: =IF(D22="","",$B$6) | H22: =IF(D22="","",IF(AND(N(F22)>0,N(G22)>0),"ERROR — debit AND credit",IF(AND(N(F22)=0,N(G22)=0),"ERROR — no amount","OK"))) | J22: =IF(D22="","",IF(COUNTIF('1. Chart of Accounts'!$F$6:$F$505,D22)=0,"NOT ON CHART OF ACCOUNTS","Found on COA"))
... A510: =IF(D510="","",$B$4) | B510: =IF(D510="","",$B$5) | C510: =IF(D510="","",$B$6) | H510: =IF(D510="","",IF(AND(N(F510)>0,N(G510)>0),"ERROR — debit AND credit",IF(AND(N(F510)=0,N(G510)=0),"ERROR — no amount","OK"))) | J510: =IF(D510="","",IF(COUNTIF('1. Chart of Accounts'!$F$6:$F$505,D510)=0,"NOT ON CHART OF ACCOUNTS","Found on COA"))

Sheet Example
A1: Example (do not send this sheet as your data)
A2: Sample microfinance chart and a balanced opening trial balance. Copy the idea, not necessarily the codes.
A3: This is a simplified illustration only. Use your real GL codes and names. Note the Opening Balances Contra equity account — CBS uses an equity contra account when loading opening balances.
A5: Example chart of accounts
A6: Account Type* | B6: Account Name* | C6: Account Usage* | D6: Manual entries allowed* | E6: Parent GL Code | F6: GL Code* | G6: Tag* | H6: Description*
A7: ASSET | B7: Assets | C7: HEADER | D7: False | F7: 1000 | G7: Default | H7: All asset accounts
A8: ASSET | B8: Cash and Bank | C8: HEADER | D8: False | E8: 1000 | F8: 1100 | G8: Cash | H8: Cash and bank parent
A9: ASSET | B9: Cash on Hand | C9: DETAIL | D9: True | E9: 1100 | F9: 1101 | G9: Cash | H9: Till / vault cash
A10: ASSET | B10: Bank — Current Account | C10: DETAIL | D10: True | E10: 1100 | F10: 1102 | G10: Bank | H10: Operating bank account
A11: ASSET | B11: Loan Portfolio | C11: HEADER | D11: False | E11: 1000 | F11: 1200 | G11: Loan Portfolio | H11: Gross loan book parent
A12: ASSET | B12: Loans Outstanding | C12: DETAIL | D12: False | E12: 1200 | F12: 1201 | G12: Loan Portfolio | H12: Principal outstanding
A13: ASSET | B13: Interest Receivable | C13: DETAIL | D13: False | E13: 1200 | F13: 1202 | G13: Interest Receivable | H13: Accrued interest on loans
A14: LIABILITY | B14: Liabilities | C14: HEADER | D14: False | F14: 2000 | G14: Default | H14: All liability accounts
A15: LIABILITY | B15: Client Savings | C15: DETAIL | D15: False | E15: 2000 | F15: 2101 | G15: Client Savings | H15: Voluntary savings
A16: LIABILITY | B16: Accounts Payable | C16: DETAIL | D16: True | E16: 2000 | F16: 2201 | G16: Payables | H16: Suppliers and accruals
A17: EQUITY | B17: Equity | C17: HEADER | D17: False | F17: 3000 | G17: Default | H17: All equity accounts
A18: EQUITY | B18: Share Capital | C18: DETAIL | D18: True | E18: 3000 | F18: 3101 | G18: Share Capital | H18: Paid-in capital
A19: EQUITY | B19: Retained Earnings | C19: DETAIL | D19: True | E19: 3000 | F19: 3201 | G19: Retained Earnings | H19: Accumulated surplus
A20: EQUITY | B20: Opening Balances Contra | C20: DETAIL | D20: False | E20: 3000 | F20: 3901 | G20: Opening Balances Contra | H20: CBS opening-balance contra (equity)
A21: INCOME | B21: Income | C21: HEADER | D21: False | F21: 4000 | G21: Default | H21: All income accounts
A22: INCOME | B22: Interest Income on Loans | C22: DETAIL | D22: False | E22: 4000 | F22: 4101 | G22: Interest Income | H22: Interest earned
A23: EXPENSE | B23: Expenses | C23: HEADER | D23: False | F23: 5000 | G23: Default | H23: All expense accounts
A24: EXPENSE | B24: Salaries and Wages | C24: DETAIL | D24: True | E24: 5000 | F24: 5101 | G24: Operating Expense | H24: Staff costs
A27: Example opening trial balance (as at 31/12/2025, Head Office, USD)
A28: Office Name* | B28: As-at Date* | C28: Currency* | D28: GL Code* | E28: Account Name | F28: Debit | G28: Credit | I28: Why this side
A29: Head Office | B29: 2025-12-31 | C29: USD | D29: 1101 | E29: Cash on Hand | F29: 25000 | I29: Asset — debit
A30: Head Office | B30: 2025-12-31 | C30: USD | D30: 1102 | E30: Bank — Current Account | F30: 180000 | I30: Asset — debit
A31: Head Office | B31: 2025-12-31 | C31: USD | D31: 1201 | E31: Loans Outstanding | F31: 1500000 | I31: Asset — debit
A32: Head Office | B32: 2025-12-31 | C32: USD | D32: 1202 | E32: Interest Receivable | F32: 15000 | I32: Asset — debit
A33: Head Office | B33: 2025-12-31 | C33: USD | D33: 2101 | E33: Client Savings | G33: 900000 | I33: Liability — credit
A34: Head Office | B34: 2025-12-31 | C34: USD | D34: 2201 | E34: Accounts Payable | G34: 20000 | I34: Liability — credit
A35: Head Office | B35: 2025-12-31 | C35: USD | D35: 3101 | E35: Share Capital | G35: 200000 | I35: Equity — credit
A36: Head Office | B36: 2025-12-31 | C36: USD | D36: 3201 | E36: Retained Earnings | G36: 600000 | I36: Equity — credit
A38: Status: both totals are 1,720,000 — BALANCED | E38: Totals | F38: =SUM(F29:F36) | G38: =SUM(G29:G36)
A40: HEADER accounts (1000, 1100, 1200, 2000, 3000, 4000, 5000) are not on the trial balance. Income (4101) and expense (5101) are zero at year-end in this example so they are omitted. If you cut over mid-year, include YTD income (credit) and YTD expense (debit) so the TB still balances.

Sheet _Lists
A1: AccountType | B1: AccountUsage | C1: YesNo | D1: Currency | E1: TagExamples
A2: ASSET | B2: DETAIL | C2: True | D2: USD | E2: Default
A3: LIABILITY | B3: HEADER | C3: False | D3: ZWG | E3: Cash
A4: EQUITY | D4: ZAR | E4: Bank
A5: INCOME | D5: GBP | E5: Loan Portfolio
A6: EXPENSE | D6: EUR | E6: Interest Receivable
E7: Fixed Assets
E8: Client Savings
E9: Payables
E10: Share Capital
E11: Retained Earnings
E12: Opening Balances Contra
E13: Interest Income
E14: Fee Income
E15: Interest Expense
E16: Operating Expense
