Workbook

Sheet COMPREHENSIVE INCOME
A1: MFI9-TOP BORROWERS-L9001
A3: Institution:
A4: Financial Year:
A5: Start Date:
A6: End Date:
A8: STATEMENT OF COMPREHENSIVE INCOME (reporting is on a cummulative basis for current year)
C10: CONSOLIDATED
A11: 1 INTEREST INCOME FROM LOANS & ADVANCES (Sum of 1.1 to 1.3) | C11: =C12+C13+C14 -> 0
A12: 1.1 CONSUMER
A13: 1.2 COMMERCIAL
A14: 1.3 OTHER
A15: 2 INTEREST INCOME AND DISCOUNT RECEIVED FROM INVESTMENTS(Sum of 2.1 to 2.9) | C15: =C16+C17+C18+C19+C20+C21+C22+C22+C23+C24 -> 0
A16: 2.1 BANK BALANCES
A17: 2.2 TREASURY BILLS
A18: 2.3 COMMERCIAL PAPER
A19: 2.4 BANKERS ACCEPTANCES
A20: 2.5 NEGOTIABLE CERTIFICATES OF DEPOSITS
A21: 2.6 GOVERNMENT BONDS
A22: 2.7 LOCAL GOVERNMENT BONDS
A23: 2.8 CORPORATE BONDS
A24: 2.9 OTHER
A25: 3 TOTAL INTEREST INCOME (Sum of 1 and 2) | C25: =C11+C15 -> 0
A26: 4 NON - INTEREST INCOME (Sum of 4.1 to 4.4) | C26: =SUM(C27:C30) -> 0
A27: 4.1 ADMINSTRATION FEES
A28: 4.2 PENALTY FEES
A29: 4.3 INSURANCE INCOME FEES
A30: 4.4 OTHER
A31: 5 TOTAL OPERATING INCOME (Sum of 3 and 4) | C31: =C25+C26 -> 0
A32: 6 INTEREST EXPENSES (Sum of 6.1 to 6.3) | C32: =SUM(C33:C35) -> 0
A33: 6.1 INTEREST AND FEES ON COMMERCIAL DEBT
A34: 6.2 INTEREST ON CONCESSIONAL DEBT
A35: 6.3 INTEREST ON SHAREHOLDERS LOANS
A36: 7 NET INTEREST INCOME ( 3 minus 6) | C36: =C25-C32 -> 0
A37: 8 PROVISION FOR LOAN LOSSES | C37: =C38+C39 -> 0
A38: 8.1 SPECIFIC
A39: 8.2 GENERAL
A40: 9 OPERATING EXPENSES (Sum of 9.1 to 9.8) | C40: =SUM(C41:C48) -> 0
A41: 9.1 SALARIES AND EMPLOYEE BENEFITS
A42: 9.2 RENT AND OCCUPATIONAL EXPENSES
A43: 9.3 DIRECTORS FEES
A44: 9.4 TRAVEL
A45: 9.5 DEPRECIATION
A46: 9.6 MARKETING
A47: 9.7 ADMINISTRATION. EXPENSES
A48: 9.8 OTHER
A49: 10 TOTAL OPERATING EXPENSES (Sum of 9 plus 8 plus 6) | C49: =C40+C37+C32 -> 0
A50: 11 NET INCOME FROM OPERATIONS ( 5 minus 10) | C50: =C31-C49 -> 0
A51: 12 GRANT INCOME | C51: 0
A52: 13 TOTAL INCOME BEFORE TAX (Sum of 11 plus 12) | C52: =C50+C51 -> 0
A53: 14 TAXATION
A54: 15 NET INCOME AFTER TAX | C54: =C52-C53 -> 0
A55: 16 DIVIDEND
A56: 17 RETAINED EARNINGS FROM OPERATIONS | C56: =C54-C55 -> 0
A58: 18 OTHER COMPREHENSIVE INCOME | C58: =SUM(C59:C61) -> 0
A59: 18.1 GAINS/(LOSSES) ON AVAILABLE FOR SALE FINANCIAL ASSETS
A60: 18.2 GAINS/ (LOSSES) ON REVALUATUION OF FIXED ASSETS
A61: 18.3 OTHER (SPECIFY)
A62: 19 TOTAL COMPREHENSIVE INCOME FOR THE YEAR | C62: =C56+C58 -> 0

Sheet STATEMENT OF FIN POSITION
A1: MFI2-SFP-L2001
A3: Institution: | B3: ='COMPREHENSIVE INCOME'!B3
A4: Financial Year: | B4: ='COMPREHENSIVE INCOME'!B4 -> 0
A5: Start Date: | B5: ='COMPREHENSIVE INCOME'!B5 -> 0
A6: End Date: | B6: ='COMPREHENSIVE INCOME'!B6 -> 0
A8: BALANCE SHEET
C10: TOTAL AMOUNT($)
A11: 1. ASSETS | C11: =SUM(C12:C13) -> 0
A12: 1.1 CASH ON HAND
A13: 1.2 CASH IN BANK (S)
A14: 1.2 FINANCIAL ASSETS HELD FOR TRADING (SUM of 1.2.1 to 1.2.5) | C14: =SUM(C15:C19) -> 0
A15: 1.2.1 TREASURY BILLS
A16: 1.2.2 NEGOTIABLE CERTIFICATES OF DEPOSITS
A17: 1.2.3 BANKERS ACCEPTANCES
A18: 1.2.4 COMMERCIAL PAPER
A19: 1.2.5 OTHER
A20: 1.3 TOTAL LOANS-Gross (Sum of 1.3.1 to 1.3.3) | C20: =C21+C22+C32 -> 0
A21: 1.3.1 CONSUMER
A22: 1.3.2 COMMERCIAL | C22: =SUM(C23:C31) -> 0
A23: (i) Farming
A24: (ii) Manufacturing
A25: (iii) Mining
A26: (iv) Services
A27: (v) Retail
A28: (vi) Transport
A29: (vii) Health
A30: (viii) Education
A31: (ix) Construction
A32: 1.3.3 OTHER
A33: 1.3.4 TOTAL PROVISIONS (GEN & SPECIFIC)
A34: 1.4 NET LOAN PORTFOLIO (1.3 minus 1.3.4) | C34: =SUM(C20-C33) -> 0
A35: 1.5 OTHER SHORT-TERM ASSETS
A36: 1.6 TOTAL CURRENT ASSETS (Sum of 1.1 to 1.5) | C36: =SUM(C11+C14+C34+C35) -> 0
A37: 1.7 FIXED ASSETS
C38: =C36+C37 -> 0
A40: 2. LIABILITIES
A41: 2.1 SHORT TERM DEBT (Sum of 2.2.1 to 2.2.3) | C41: =SUM(C42+C43) -> 0
A42: 2.1.1 COMMERCIAL RATES
A43: 2.1.2 CONCESSIONAL RATES
A44: 2.2.TAXATION
A45: 2.3 DIVIDENDS PAYABLE
A46: 2.4 OTHER CURRENT LIABILITIES
A48: 2.5 TOTAL CURRENT LIABILITIES (Sum of 2.1 to 2.4) | C48: =SUM(C42:C46) -> 0
A50: 2.6 SHAREHOLDER LOANS
A52: 2.7 LONG TERM DEBT (Sum of 2.7.1 to 2.7.3) | C52: =SUM(C53+C54+C55) -> 0
A53: 2.7.1 COMMERCIAL RATES
A54: 2.7.2 CONCESSIONAL RATES
A55: 2.7.3 OTHER LONG TERM LIABILITIES
A56: 2.8 TOTAL LIABILITIES (Sum of 2.5 to 2.7 ) | C56: =SUM(C48:C52) -> 0
A58: 3. EQUITY (Sum of 3.1 to 3.8) | C58: =SUM(C59+C60+C61+C62+C63+C64+C65+C66) -> 0
A59: 3.1. ORDINARY SHARES (PAR VALUE)
A60: 3.2. SHARE PREMIUM ACCOUNT
A61: 3.3 IRREDEEMABLE CUMULATIVE PREFERENCE SHARES
A62: 3.4 IRREDEEMABLE NON CUMULATIVE PREFERENCE SHARES
A63: 3.5 REVALUATION RESERVES
A64: 3.6. DONATED EQUITY/ GRANTS
A65: 3.7. OTHER RESERVES
A66: 3.8. PROFIT AND LOSS/RETAINED EARNINGS | C66: =C67+C68 -> 0
A67: 3.8.1 CURRENT YEAR
A68: 3.8.2 PRIOR YEARS
A69: 4. TOTAL LIABILITIES AND EQUITY (Sum of 2 plus 3) | C69: =C58+C56 -> 0

Sheet SCHEDULE 1 INSIDER LOANS
A1: MFI3-INSIDER LOANS-L3001
A3: Institution: | B3: ='COMPREHENSIVE INCOME'!B3
A4: Financial Year: | B4: ='COMPREHENSIVE INCOME'!B4 -> 0
A5: Start Date: | B5: ='COMPREHENSIVE INCOME'!B5 -> 0
A6: End Date: | B6: ='COMPREHENSIVE INCOME'!B6 -> 0
A9: SCHEDULE 1 - INSIDER LOANS TO SHAREHOLDERS, DIRECTORS, AND OTHER RELATED PARTIES
A10: Name of borrower | B10: Relationship to institution | C10: Total limit | D10: Amount Outstanding | E10: Interest rate | F10: Type of Security | G10: Value of security
A11: TOTAL | C11: =SUM(C12:C31) -> 0 | D11: =SUM(D12:D31) -> 0 | G11: =SUM(G12:G31) -> 0

Sheet SCHEDULE 2 LONG TERM DEB
A1: MFI4-LONG TERM DEBT-L4001
A3: Institution: | B3: ='COMPREHENSIVE INCOME'!B3
A4: Financial Year: | B4: ='COMPREHENSIVE INCOME'!B4 -> 0
A5: Start Date: | B5: ='COMPREHENSIVE INCOME'!B5 -> 0
A6: End Date: | B6: ='COMPREHENSIVE INCOME'!B6 -> 0
A8: SCHEDULE 2 - LONG TERM DEBT
A9: Source of Finance | B9: Amount Borrowed | C9: Outstanding Bal | D9: Interest Rate | E9: Maturity Date
A10: Total | B10: =SUM(B11:B30) -> 0 | C10: =SUM(C11:C30) -> 0

Sheet SCHEDULE 3 ASSET QUALITY
A1: MFI-ASSET.QUALITY-L0001
A3: Institution: | B3: ='COMPREHENSIVE INCOME'!B3
A4: Financial Year: | B4: ='COMPREHENSIVE INCOME'!B4 -> 0
A5: Start Date: | B5: ='COMPREHENSIVE INCOME'!B5 -> 0
A6: End Date: | B6: ='COMPREHENSIVE INCOME'!B6 -> 0
A8: SCHEDULE 3 - ASSET QUALITY
A9: CLASSIFICATION OF LOANS
B10: DAYS OUTSTANDING/ARREARS | C10: TOTAL LOANS | D10: SUPERVISORY PROVISION % | E10: PROVISIONS AMOUNT
A12: TOTAL PASS - CURRENT | B12: 0 | C12: =SUM(C13:C15) -> 0 | D12: 0.01 | E12: =D12*C12 -> 0
A13: CONSUMER LOANS | D13: 0.01 | E13: =D13*C13 -> 0
A14: COMMERCIAL LOANS | D14: 0.01 | E14: =D14*C14 -> 0
A15: OTHER LOANS | D15: 0.01 | E15: =D15*C15 -> 0
A16: TOTAL SPECIAL MENTION | B16: 1-30 Days | C16: =SUM(C17:C19) -> 0 | D16: 0.2 | E16: =D16*C16 -> 0
A17: CONSUMER LOANS | D17: 0.2 | E17: =D17*C17 -> 0
A18: COMMERCIAL LOANS | D18: 0.2 | E18: =D18*C18 -> 0
A19: OTHER LOANS | D19: 0.2 | E19: =D19*C19 -> 0
A20: TOTAL SUBSTANDARD | B20: 31-60 Days | C20: =SUM(C21:C23) -> 0 | D20: 0.5 | E20: =D20*C20 -> 0
A21: CONSUMER LOANS | D21: 0.5 | E21: =D21*C21 -> 0
A22: COMMERCIAL LOANS | D22: 0.5 | E22: =D22*C22 -> 0
A23: OTHER LOANS | D23: 0.5 | E23: =D23*C23 -> 0
A24: TOTAL DOUBTFUL | B24: 61 - 90 days | C24: =SUM(C25:C27) -> 0 | D24: 0.75 | E24: =D24*C24 -> 0
A25: CONSUMER LOANS | D25: 0.75 | E25: =D25*C25 -> 0
A26: COMMERCIAL LOANS | D26: 0.75 | E26: =D26*C26 -> 0
A27: OTHER LOANS | D27: 0.75 | E27: =D27*C27 -> 0
A28: TOTAL LOSS | B28: +91days | C28: =SUM(C29:C31) -> 0 | D28: 1 | E28: =D28*C28 -> 0
A29: CONSUMER LOANS | D29: 1 | E29: =D29*C29 -> 0
A30: COMMERCIAL LOANS | D30: 1 | E30: =D30*C30 -> 0
A31: OTHER LOANS | D31: 1 | E31: =D31*C31 -> 0
A32: GRAND TOTAL | C32: =C28+C24+C20+C16+C12 -> 0 | E32: =E33+E34 -> 0
A33: SPECIFIC PROVISIONS | E33: =E20+E24+E28 -> 0
A34: GENERAL PROVISIONS | E34: =E12+E16 -> 0

Sheet SCHEDULE 4 DISTRIBUTION 
A1: MFI-LOAN.DISTRIBUTE-LE001
A3: Institution: | B3: ='COMPREHENSIVE INCOME'!B3
A4: Financial Year: | B4: ='COMPREHENSIVE INCOME'!B4 -> 0
A5: Start Date: | B5: ='COMPREHENSIVE INCOME'!B5 -> 0
A6: End Date: | B6: ='COMPREHENSIVE INCOME'!B6 -> 0
A8: SCHEDULE 4 - DISTRIBUTION OF LOANS & ADVANCES
A9: PURPOSE OF LOAN | B9: NUMBER OF CLIENTS | C9: NUMBER OF LOANS | D9: VALUE | E9: PERCENTAGE OF TOTAL LOANS
A10: TOTAL | B10: =SUM(B11:B23) -> 0 | C10: =SUM(C11:C23) -> 0 | D10: =SUM(D11:D23) -> 0 | E10: =SUM(E11:E23) -> #DIV/0!
A11: DISTRIBUTION | E11: =D11/D10 -> #DIV/0!
A12: MANUFACTURING | E12: =+D12/D10 -> #DIV/0!
A13: RETAIL | E13: =+D13/D10 -> #DIV/0!
A14: CONSUMPTION | E14: =+D14/D10 -> #DIV/0!
A15: SERVICES | E15: =+D15/D10 -> #DIV/0!
A16: HEALTH | E16: =+D16/D10 -> #DIV/0!
A17: EDUCATION | E17: =+D17/D10 -> #DIV/0!
A18: MINING | E18: =+D18/D10 -> #DIV/0!
A19: AGRICULTURE | E19: =+D19/D10 -> #DIV/0!
A20: CROSS BORDER TRADERS | E20: =+D20/D10 -> #DIV/0!
A21: VENDORS | E21: =+D21/D10 -> #DIV/0!
A22: FUNERAL ASSISTANCE | E22: =+D22/D11 -> #DIV/0!
A23: OTHER | E23: =+D23/D10 -> #DIV/0!

Sheet SCHEDULE 5 GENDER DISTRIBUTION
A1: MFI-GENDER.DISTRIBU-LF001
A3: Institution: | B3: ='COMPREHENSIVE INCOME'!B3
A4: Financial Year: | B4: ='COMPREHENSIVE INCOME'!B4 -> 0
A5: Start Date: | B5: ='COMPREHENSIVE INCOME'!B5 -> 0
A6: End Date: | B6: ='COMPREHENSIVE INCOME'!B6 -> 0
A8: SCHEDULE 5 - GENDER DISTRIBUTION OF LOANS & ADVANCES
A9: PURPOSE OF LOAN | B9: NUMBER OF FEMALE CLIENTS | C9: TOTAL NUMBER OF LOANS | D9: VALUE | E9: PERCENTAGE OF TOTAL LOANS
A10: TOTAL | B10: =SUM(B11:B23) -> 0 | C10: =SUM(C11:C23) -> 0 | D10: =SUM(D11:D23) -> 0 | E10: =SUM(E11:E23) -> #DIV/0!
A11: DISTRIBUTION | E11: =D11/D10 -> #DIV/0!
A12: MANUFACTURING | E12: =+D12/D10 -> #DIV/0!
A13: RETAIL | E13: =+D13/D10 -> #DIV/0!
A14: CONSUMPTION | E14: =+D14/D10 -> #DIV/0!
A15: SERVICES | E15: =+D15/D10 -> #DIV/0!
A16: HEALTH | E16: =+D16/D10 -> #DIV/0!
A17: EDUCATION | E17: =+D17/D10 -> #DIV/0!
A18: MINING | E18: =+D18/D10 -> #DIV/0!
A19: AGRICULTURE | E19: =+D19/D10 -> #DIV/0!
A20: CROSS BORDER TRADERS | E20: =+D20/D10 -> #DIV/0!
A21: VENDORS | E21: =+D21/D10 -> #DIV/0!
A22: FUNERAL ASSISTANCE | E22: =+D22/D11 -> #DIV/0!
A23: OTHER | E23: =+D23/D10 -> #DIV/0!

Sheet SCHEDULE 6 MATURITY PROF
A1: MFI8-MATURITY PROF-L8001
A3: Institution: | B3: ='COMPREHENSIVE INCOME'!B3
A4: Financial Year: | B4: ='COMPREHENSIVE INCOME'!B4 -> 0
A5: Start Date: | B5: ='COMPREHENSIVE INCOME'!B5 -> 0
A6: End Date: | B6: ='COMPREHENSIVE INCOME'!B6 -> 0
A8: SCHEDULE 6 - MATURITY PROFILE (Asset and Liability Maturities)
B10: CASH INFLOWS | C10: CASH OUTFLOWS (Maturing Liabilities) | D10: Net position | E10: Cumulative Position
A11: TOTAL INFLOWS/OUTFLOWS | B11: =SUM(B15:B19) -> 0 | C11: =SUM(C15:C19) -> 0 | D11: =B11-C11 -> 0 | E11: =D11 -> 0
A12: i) 0-7 days | D12: =B12-C12 -> 0 | E12: =D12 -> 0
A13: ii) 8 - 14 days | D13: =B13-C13 -> 0 | E13: =E12+D13 -> 0
A14: iii) 15 -30 days | D14: =B14-C14 -> 0 | E14: =E13+D14 -> 0
A15: iv) 31-60 days | D15: =B15-C15 -> 0 | E15: =E14+D15 -> 0
A16: v) 61-90 days | D16: =B16-C16 -> 0 | E16: =E15+D16 -> 0
A17: vi) 91-120 days | D17: =B17-C17 -> 0 | E17: =E16+D17 -> 0
A18: vii) 121-180 days | D18: =B18-C18 -> 0 | E18: =E17+D18 -> 0
A19: viii) 181-360 days | D19: =B19-C19 -> 0 | E19: =E18+D19 -> 0

Sheet SCHEDULE 7 TOP 20 BORROW
A1: MFI9-TOP BORROWERS-L9001
A3: Institution: | B3: ='COMPREHENSIVE INCOME'!B3
A4: Financial Year: | B4: ='COMPREHENSIVE INCOME'!B4 -> 0
A5: Start Date: | B5: ='COMPREHENSIVE INCOME'!B5 -> 0
A6: End Date: | B6: ='COMPREHENSIVE INCOME'!B6 -> 0
C8: SCHEDULE 7 - T0P TWENTY BORROWERS
A9: NAME OF BORROWER | B9: TOTAL AMOUNT BORROWED | C9: BALANCE OUTSTANDING | D9: MATURITY DATE | E9: TYPE OF SECURITY | F9: VALUE OF SECURITY
A10: TOTAL | B10: =SUM(B11:B30) -> 0 | C10: =SUM(C11:C30) -> 0 | F10: =SUM(F11:F30) -> 0

Sheet SCHEDULE 8 - ACCESS BY DISTRICT
A1: DTMFI-ABDDK002
A3: Institution: | B3: ='COMPREHENSIVE INCOME'!B3
A4: Financial Year: | B4: ='COMPREHENSIVE INCOME'!B4 -> 0
A5: Start Date: | B5: ='COMPREHENSIVE INCOME'!B5 -> 0
A6: End Date: | B6: ='COMPREHENSIVE INCOME'!B6 -> 0
A8: ACCESS BY DISTRICT | C8: DELIVERY CHANNELS | O8: VALUE($)
A10: PROVINCE | B10: DISTRICTS | C10: Number of Rural Branches | D10: Number of Urban branches | E10: Number of Rural POS | F10: Number of Urban POS | G10: Number of Rural ATMs | H10: Number of Urban ATMs | I10: Number of Rural Agencies | J10: Number of Urban Agencies | K10: Number of Mobile Rural Branches | L10: Number of Mobile Urban branches | M10: Number of Rural Satellite/ Sub Branches | N10: Number of Urban Satellite/ Sub Branches | O10: POS (VALUE) | P10: ATMs (VALUE) | Q10: Internet (VALUE) | R10: RTGS/Transfers POS (VALUE) | S10: Mobile POS (VALUE) | T10: Other (VALUE)
A11: BULAWAYO | B11: BULAWAYO-Bulawayo
A12: HARARE | B12: HARARE-Chitungwiza
B13: HARARE-Harare
B14: HARARE-Total | C14: =C12+C13 -> 0 | D14: =D12+D13 -> 0 | E14: =E12+E13 -> 0 | F14: =F12+F13 -> 0 | G14: =G12+G13 -> 0 | H14: =H12+H13 -> 0 | I14: =I12+I13 -> 0 | J14: =J12+J13 -> 0 | ... T14: =T12+T13 -> 0
A15: MANICALAND | B15: MANICALAND-Buhera
B16: MANICALAND-Chimanimani
B17: MANICALAND-Chipinge
B18: MANICALAND-Makoni
B19: MANICALAND-Mutare
B20: MANICALAND-Mutasa
B21: MANICALAND-Nyanga
B22: MANICALAND-Total | C22: =SUM(C15:C21) -> 0 | D22: =SUM(D15:D21) -> 0 | E22: =SUM(E15:E21) -> 0 | F22: =SUM(F15:F21) -> 0 | G22: =SUM(G15:G21) -> 0 | H22: =SUM(H15:H21) -> 0 | I22: =SUM(I15:I21) -> 0 | J22: =SUM(J15:J21) -> 0 | ... T22: =SUM(T15:T21) -> 0
A23: MASHONALAND CENTRAL | B23: MASHONALAND CENTRAL-Bindura
B24: MASHONALAND CENTRAL-Guruve
B25: MASHONALAND CENTRAL-Mazowe
B26: MASHONALAND CENTRAL-Mbire
B27: MASHONALAND CENTRAL-Mukumbura
B28: MASHONALAND CENTRAL-Muzarabani
B29: MASHONALAND CENTRAL-Rushinga
B30: MASHONALAND CENTRAL-Shamva
B31: MASHONALAND CENTRAL-Total | C31: =SUM(C23:C30) -> 0 | D31: =SUM(D23:D30) -> 0 | E31: =SUM(E23:E30) -> 0 | F31: =SUM(F23:F30) -> 0 | G31: =SUM(G23:G30) -> 0 | H31: =SUM(H23:H30) -> 0 | I31: =SUM(I23:I30) -> 0 | J31: =SUM(J23:J30) -> 0 | ... T31: =SUM(T23:T30) -> 0
A32: MASHONALAND EAST | B32: MASHONALAND EAST-Chikomba
B33: MASHONALAND EAST-Goromonzi
B34: MASHONALAND EAST-Hwedza
B35: MASHONALAND EAST-Marondera
B36: MASHONALAND EAST-Mudzi
B37: MASHONALAND EAST-Murehwa
B38: MASHONALAND EAST-Mutoko
B39: MASHONALAND EAST-Seke
B40: MASHONALAND EAST-Uzumba
B41: MASHONALAND EAST-Total | C41: =SUM(C32:C40) -> 0 | D41: =SUM(D32:D40) -> 0 | E41: =SUM(E32:E40) -> 0 | F41: =SUM(F32:F40) -> 0 | G41: =SUM(G32:G40) -> 0 | H41: =SUM(H32:H40) -> 0 | I41: =SUM(I32:I40) -> 0 | J41: =SUM(J32:J40) -> 0 | ... T41: =SUM(T32:T40) -> 0
A42: MASHONALAND WEST | B42: MASHONALAND WEST-Chegutu
B43: MASHONALAND WEST-Hurungwe
B44: MASHONALAND WEST-Kadoma
B45: MASHONALAND WEST-Kariba
B46: MASHONALAND WEST-Makonde
B47: MASHONALAND WEST-Zvimba
B48: MASHONALAND WEST-Total | C48: =SUM(C42:C47) -> 0 | D48: =SUM(D42:D47) -> 0 | E48: =SUM(E42:E47) -> 0 | F48: =SUM(F42:F47) -> 0 | G48: =SUM(G42:G47) -> 0 | H48: =SUM(H42:H47) -> 0 | I48: =SUM(I42:I47) -> 0 | J48: =SUM(J42:J47) -> 0 | ... T48: =SUM(T42:T47) -> 0
A49: MASVINGO | B49: MASVINGO-Bikita
B50: MASVINGO-Chiredzi
B51: MASVINGO-Chivi
B52: MASVINGO-Gutu
B53: MASVINGO-Masvingo
B54: MASVINGO-Mwenezi
B55: MASVINGO-Zaka
B56: MASVINGO-Total | C56: =SUM(C49:C55) -> 0 | D56: =SUM(D49:D55) -> 0 | E56: =SUM(E49:E55) -> 0 | F56: =SUM(F49:F55) -> 0 | G56: =SUM(G49:G55) -> 0 | H56: =SUM(H49:H55) -> 0 | I56: =SUM(I49:I55) -> 0 | J56: =SUM(J49:J55) -> 0 | ... T56: =SUM(T49:T55) -> 0
A57: MATEBELELAND NORTH | B57: MATEBELELAND NORTH-Binga
B58: MATEBELELAND NORTH-Bubi
B59: MATEBELELAND NORTH-Hwange
B60: MATEBELELAND NORTH-Lupane
B61: MATEBELELAND NORTH-Nkayi
B62: MATEBELELAND NORTH-Tsholotsho
B63: MATEBELELAND NORTH-Umguza
B64: MATEBELELAND NORTH-Total | C64: =SUM(C57:C63) -> 0 | D64: =SUM(D57:D63) -> 0 | E64: =SUM(E57:E63) -> 0 | F64: =SUM(F57:F63) -> 0 | G64: =SUM(G57:G63) -> 0 | H64: =SUM(H57:H63) -> 0 | I64: =SUM(I57:I63) -> 0 | J64: =SUM(J57:J63) -> 0 | ... T64: =SUM(T57:T63) -> 0
A65: MATEBELELAND SOUTH | B65: MATEBELELAND SOUTH-Beitbridge
B66: MATEBELELAND SOUTH-Bulilimamangwe
B67: MATEBELELAND SOUTH-Gwanda
B68: MATEBELELAND SOUTH-Insiza
B69: MATEBELELAND SOUTH-Makobo
B70: MATEBELELAND SOUTH-Umzingwane
B71: MATEBELELAND SOUTH-Insiza
B72: MATEBELELAND SOUTH-Total | C72: =SUM(C65:C71) -> 0 | D72: =SUM(D65:D71) -> 0 | E72: =SUM(E65:E71) -> 0 | F72: =SUM(F65:F71) -> 0 | G72: =SUM(G65:G71) -> 0 | H72: =SUM(H65:H71) -> 0 | I72: =SUM(I65:I71) -> 0 | J72: =SUM(J65:J71) -> 0 | ... T72: =SUM(T65:T71) -> 0
A73: MIDLANDS | B73: MIDLANDS-Chirumhanzi
B74: MIDLANDS-Gokwe North
B75: MIDLANDS-Gokwe South
B76: MIDLANDS-Gweru
B77: MIDLANDS-Kwekwe
B78: MIDLANDS-Mberengwa
B79: MIDLANDS-Shurungwi
B80: MIDLANDS-Zvishavane
B81: MIDLANDS-Total | C81: =SUM(C73:C80) -> 0 | D81: =SUM(D73:D80) -> 0 | E81: =SUM(E73:E80) -> 0 | F81: =SUM(F73:F80) -> 0 | G81: =SUM(G73:G80) -> 0 | H81: =SUM(H73:H80) -> 0 | I81: =SUM(I73:I80) -> 0 | J81: =SUM(J73:J80) -> 0 | ... T81: =SUM(T73:T80) -> 0
B82: Grand Totals | C82: =+C11+C14+C22+C31+C41+C48+C56+C64+C72+C81 -> 0 | D82: =+D11+D14+D22+D31+D41+D48+D56+D64+D72+D81 -> 0 | E82: =+E11+E14+E22+E31+E41+E48+E56+E64+E72+E81 -> 0 | F82: =+F11+F14+F22+F31+F41+F48+F56+F64+F72+F81 -> 0 | G82: =+G11+G14+G22+G31+G41+G48+G56+G64+G72+G81 -> 0 | H82: =+H11+H14+H22+H31+H41+H48+H56+H64+H72+H81 -> 0 | I82: =+I11+I14+I22+I31+I41+I48+I56+I64+I72+I81 -> 0 | J82: =+J11+J14+J22+J31+J41+J48+J56+J64+J72+J81 -> 0 | ... T82: =+T11+T14+T22+T31+T41+T48+T56+T64+T72+T81 -> 0

Sheet SCHEDULE 9 PORT MNGMNT
A1: MFI-PORTFOLIO.MNGMT-LG001
A3: Institution: | B3: ='COMPREHENSIVE INCOME'!B3
A4: Financial Year: | B4: ='COMPREHENSIVE INCOME'!B4 -> 0
A5: Start Date: | B5: ='COMPREHENSIVE INCOME'!B5 -> 0
A6: End Date: | B6: ='COMPREHENSIVE INCOME'!B6 -> 0
A8: SCHEDULE 8 - PORTFOLIO MANAGEMENT
A10: 1 PORTFOLIO ACTIVITY | C10: VALUE/NUMBER
A11: 1.1 NUMBER OF LOANS DISBURSED
A12: 1.2 VALUE OF LOANS DISBURSED
A13: 1.3 NUMBER OF CLIENTS TAKING FIRST LOAN
A14: 1.4 NUMBER OF CLIENTS TAKING SECOND AND SUBSEQUENT LOANS
A15: 1.5 NUMBER OF ACTIVE CLIENTS AT START OF QUARTER
A16: 1.6 NUMBER OF ACTIVE CLIENTS AT END OF QUARTER
A17: 1.7 DROP OUT/GROWTH RATE (%) | C17: =C15/C16 -> #DIV/0!
A18: 1.8 NUMBER OF OUTSTANDING LOANS
A19: 1.9 AVERAGE LOAN TERM IN MONTHS
A20: 1.10 TOTAL NUMBER OF ALL CLIENTS (ACTIVE + NON ACTIVE)
A21: 2. OUTREACH
A22: 2.1 NUMBER OF BRANCHES
A23: 2.1.1 URBAN
A24: 2.1.2 RURAL
A25: 2.2 NUMBER OF ACTIVE LOAN CLIENTS IN RURAL BRANCHES (definition)
A26: 2.3 NUMBER OF BORROWING GROUPS
A27: 2.4 NUMBER OF ACTIVE LOAN CLIENTS RECEIVING LOANS AS MEMBERS OF A GROUP
A28: 2.5 NUMBER OF ACTIVE LOAN CLIENTS RECEIVING LOANS AS INDIVIDUALS
A29: 2.6 NUMBER OF LOANS WITH A DISBURSED LOAN AMOUNT MORE THAN $5,000
... A41: 3.10 SCHEDULED AMOUNTS DUE IN PERIOD PLUS ARREARS
A42: 3.11 COLLECTION RATE (%) | C42: =(C40/C41)*100 -> #DIV/0!
A43: 3.12 VALUE OF ROLLED OVER/RENEGOTIATED LOANS
A44: 3.13 NUMBER OF ROLLED OVER/RENEGOTIATED LOANS
A45: 4. WRITE-OFFS
A46: 4.1 NUMBER OF LOANS WRITTEN OFF DURING PERIOD
A47: 4.2 VALUE OF LOANS WRITTEN OFF
A48: 4.4 NUMBER OF LOANS UNDER LITIGATION
A49: 4.5 VALUE OF LOANS UNDER LITIGATION

Sheet SCHEDULE 9 CO. PROFILE
A1: MFI11-CO PROFILE-LB001
A3: Institution: | B3: ='COMPREHENSIVE INCOME'!B3
A4: Financial Year: | B4: ='COMPREHENSIVE INCOME'!B4 -> 0
A5: Start Date: | B5: ='COMPREHENSIVE INCOME'!B5 -> 0
A6: End Date: | B6: ='COMPREHENSIVE INCOME'!B6 -> 0
A8: SCHEDULE 9 - COMPANY PROFILE
A9: 1 NAME OF INSTITUTION
A10: 2 LICENCE NUMBER
A11: 3 DATE COMMENCED OPERATIONS
A12: 4 PHYSICAL ADDRESS
A13: 5 POSTAL ADDRESS
A14: 6 CONTACT TELEPHONES
A15: 7 CONTACT PERSON
A16: 8 NUMBER OF BRANCHES
A17: 9 NUMBER OF EMPLOYEES
A18: 9 (a) Female
A19: 9 (b) Male
... A25: 13 LAWYERS
